pykeyset-0.1.1.dist-info/METADATA
pykeyset-0.1.1.dist-info/WHEEL
pykeyset-0.1.1.dist-info/entry_points.txt
pykeyset-0.1.1.dist-info/license_files/LICENCE-APACHE
pykeyset-0.1.1.dist-info/license_files/LICENCE-MIT
pykeyset/cmdlist.py
pykeyset/core/ctx.py
pykeyset/core/font.py
pykeyset/core/icon.py
pykeyset/core/layout.py
pykeyset/core/profile.py
pykeyset/core/save.py
pykeyset/core/__init__.py
pykeyset/resources/fonts/cherry.xml
pykeyset/resources/icons/cherry.xml
pykeyset/resources/profiles/cherry.toml
pykeyset/resources/profiles/kat.toml
pykeyset/resources/__init__.py
pykeyset/utils/config.py
pykeyset/utils/logging.py
pykeyset/utils/types.py
pykeyset/utils/__init__.py
pykeyset/__init__.py
pykeyset/__main__.py
pykeyset/_impl.pyd
pykeyset-0.1.1.dist-info/RECORD
