Metadata-Version: 2.1
Name: pykeyset
Version: 0.1.1
Classifier: Programming Language :: Rust
Classifier: Programming Language :: Python :: Implementation :: CPython
Classifier: Programming Language :: Python :: Implementation :: PyPy
Requires-Dist: typer ~= 0.7.0
Requires-Dist: click ~= 8.1
Requires-Dist: rich ~= 13.0
Requires-Dist: importlib_resources ~= 1.3; python_version < '3.9'
License-File: LICENCE-APACHE
License-File: LICENCE-MIT
Author: Lucas Jansen
Requires-Python: >=3.7
